football_domain/__init__.py
football_domain-0.0.2.dist-info/WHEEL
football_domain-0.0.2.dist-info/METADATA
football_domain-0.0.2.dist-info/RECORD
