Metadata-Version: 2.1
Name: football_domain
Version: 0.0.2
Summary: Module with domain model of football.
Author-email: Paweł Samoraj <samoraj.pawel@gmail.com>
Project-URL: Home, http://samoraj.pl
